python_supremacy1914/__init__.py
python_supremacy1914/supremacy.py
python_supremacy1914/wrapper.py
supremacy1914_wrapper/__init__.py
supremacy1914_wrapper/wrapper.py
tests/__init__.py
tests/conftest.py
tests/test_supremacy1914_wrapper.py
supremacy1914_wrapper-0.1.4.dist-info/LICENSE
supremacy1914_wrapper-0.1.4.dist-info/METADATA
supremacy1914_wrapper-0.1.4.dist-info/WHEEL
supremacy1914_wrapper-0.1.4.dist-info/top_level.txt
supremacy1914_wrapper-0.1.4.dist-info/RECORD
