Metadata-Version: 2.1
Name: supremacy1914_wrapper
Version: 0.1.4
Summary: Supremacy1914 API wrapper in Python
Home-page: https://github.com/joostsijm/supremacy1914_wrapper
Author: Joost Sijm
Author-email: joostsijm@gmail.com
License: UNKNOWN
Platform: UNKNOWN
Classifier: Programming Language :: Python :: 3
Classifier: License :: OSI Approved :: Apache Software License
Classifier: Operating System :: OS Independent
